facedetection/__init__.py
facedetection/tests/__init__.py
facedetection-1.2rc1.dist-info/DESCRIPTION.rst
facedetection-1.2rc1.dist-info/METADATA
facedetection-1.2rc1.dist-info/RECORD
facedetection-1.2rc1.dist-info/WHEEL
facedetection-1.2rc1.dist-info/entry_points.txt
facedetection-1.2rc1.dist-info/metadata.json
facedetection-1.2rc1.dist-info/top_level.txt
